{
  "project_info": {
    "project_number": "831691568509",
    "project_id": "health-hour",
    "storage_bucket": "health-hour.appspot.com"
  },
  "client": [
    {
      "client_info": {
        "mobilesdk_app_id": "1:831691568509:android:05edbca1bbe4ac33538814",
        "android_client_info": {
          "package_name": "com.example.health_hour"
        }
      },
      "oauth_client": [],
      "api_key": [
        {
          "current_key": "AIzaSyCNk2Fu-bHrM4XhC0FHH7xBJtC_xGc1YZo"
        }
      ],
      "services": {
        "appinvite_service": {
          "other_platform_oauth_client": []
        }
      }
    }
  ],
  "configuration_version": "1"
}